Metadata-Version: 1.0
Name: easywebdav
Version: 1.0.3
Summary: A straight-forward WebDAV client, implemented using Requests
Home-page: http://github.com/amnong/easywebdav
Author: Amnon Grossman
Author-email: emesh1@gmail.com
License: ISC
Platform: UNKNOWN
Classifier: Development Status :: 4 - Beta
Classifier: Intended Audience :: Developers
Classifier: Programming Language :: Python :: 2.7
